sysadms_sdk/__init__.py
sysadms_sdk/hello.py
sysadms_sdk-0.0.0.dist-info/METADATA
sysadms_sdk-0.0.0.dist-info/WHEEL
sysadms_sdk-0.0.0.dist-info/top_level.txt
sysadms_sdk-0.0.0.dist-info/RECORD
