Metadata-Version: 2.1
Name: sysadms-sdk
Version: 0.0.0
Summary: Sysadms SDK
Author: Tabby.ai | Sysadms Team
Classifier: Programming Language :: Python :: 3
